MANIFEST.in
README.mkd
setup.py
test-requirements.txt
pez/__init__.py
pez.egg-info/PKG-INFO
pez.egg-info/SOURCES.txt
pez.egg-info/dependency_links.txt
pez.egg-info/not-zip-safe
pez.egg-info/top_level.txt