Metadata-Version: 1.0
Name: pez
Version: 0.0.2
Summary: PEZ - Python P(r)e-(Seriali)z(ation)
Home-page: https://github.com/balanced/pez
Author: Balanced
Author-email: dev@balancedpayments.com
License: UNKNOWN
Platform: UNKNOWN
